horuslp/__init__.py
horuslp/core/Constraint.py
horuslp/core/Metric.py
horuslp/core/Objective.py
horuslp/core/ProblemClass.py
horuslp/core/Variables.py
horuslp/core/__init__.py
horuslp/core/constants.py
horuslp/core/utils.py
horuslp_gurobi/__init__.py
horuslp_gurobi/core/Constraint.py
horuslp_gurobi/core/Metric.py
horuslp_gurobi/core/Objective.py
horuslp_gurobi/core/ProblemClass.py
horuslp_gurobi/core/Variables.py
horuslp_gurobi/core/__init__.py
horuslp_gurobi/core/constants.py
horuslp_gurobi/core/utils.py
horuslp_gurobi-0.0.1.dist-info/LICENSE
horuslp_gurobi-0.0.1.dist-info/METADATA
horuslp_gurobi-0.0.1.dist-info/WHEEL
horuslp_gurobi-0.0.1.dist-info/top_level.txt
horuslp_gurobi-0.0.1.dist-info/RECORD
