Metadata-Version: 2.1
Name: horuslp-gurobi
Version: 0.0.1
Summary: A library to boost productivty of optimization algorithm developers. Find the source at https://github.com/shanglun/horuslp
Home-page: https://github.com/shanglun/horuslp
Author: shanglunwang
Author-email: sean.shanglun.wang@gmail.com
License: LGPL
Platform: UNKNOWN
